<?xml version="1.0" encoding="UTF-8"?>
<databaseChangeLog
        xmlns="http://www.liquibase.org/xml/ns/dbchangelog"
        xmlns:xsi="http://www.w3.org/2001/XMLSchema-instance"
        xsi:schemaLocation="http://www.liquibase.org/xml/ns/dbchangelog
                            http://www.liquibase.org/xml/ns/dbchangelog/dbchangelog-latest.xsd">

    <changeSet id="create-admins" author="Gleb Zapara">
        <sql dbms="postgresql" splitStatements="true" stripComments="true">
            <![CDATA[
            CREATE TABLE admins(
                id INTEGER PRIMARY KEY GENERATED BY DEFAULT AS IDENTITY,
                name VARCHAR(255) NOT NULL,
                surname VARCHAR(255) NOT NULL,
                email VARCHAR(255) UNIQUE NOT NULL CHECK (email ~ '^[A-Za-z0-9._%+-]+@[A-Za-z0-9.-]+\.[A-Za-z]{2,}$'),
                password VARCHAR(255) NOT NULL,
                role VARCHAR(20) NOT NULL
            );
            ]]>
        </sql>
    </changeSet>

    <changeSet id="create-departments" author="zapara">
        <sql dbms="postgresql" splitStatements="true" stripComments="true">
            <![CDATA[
            CREATE TABLE departments(
                id INTEGER PRIMARY KEY GENERATED BY DEFAULT AS IDENTITY,
                name VARCHAR(100) NOT NULL,
                number INTEGER NOT NULL
            );
            ]]>
        </sql>
    </changeSet>

    <changeSet id="create-groups" author="zapara">
        <sql dbms="postgresql" splitStatements="true" stripComments="true">
            <![CDATA[
            CREATE TABLE groups(
                id INTEGER PRIMARY KEY GENERATED BY DEFAULT AS IDENTITY,
                course SMALLINT NOT NULL CHECK (course >= 1 AND course <= 6),
                number INTEGER NOT NULL,
                speciality VARCHAR(2) NOT NULL CHECK (speciality ~ '[A-Z]+[1-8]'),
                department_id INTEGER NOT NULL REFERENCES departments(id) ON UPDATE CASCADE ON DELETE CASCADE
            );
            ]]>
        </sql>
    </changeSet>

    <changeSet id="create-teachers" author="Gleb Zapara">
        <sql dbms="postgresql" splitStatements="true" stripComments="true">
            <![CDATA[
            CREATE TABLE teachers(
                id INTEGER PRIMARY KEY GENERATED BY DEFAULT AS IDENTITY,
                name VARCHAR(255) NOT NULL,
                surname VARCHAR(255) NOT NULL,
                email VARCHAR(255) UNIQUE NOT NULL CHECK (email ~ '^[A-Za-z0-9._%+-]+@[A-Za-z0-9.-]+\.[A-Za-z]{2,}$'),
                password VARCHAR(255) NOT NULL,
                phone_number VARCHAR(16) NOT NULL CHECK (phone_number ~ '^\+[0-9]{9,15}$'),
                department_id INTEGER REFERENCES departments(id) NOT NULL,
                image VARCHAR(255),
                role VARCHAR(20) NOT NULL
            );
            ]]>
        </sql>
    </changeSet>

    <changeSet id="create-students" author="Gleb Zapara">
        <sql dbms="postgresql" splitStatements="true" stripComments="true">
            <![CDATA[
            CREATE TABLE students(
                id INTEGER PRIMARY KEY GENERATED BY DEFAULT AS IDENTITY,
                name VARCHAR(255) NOT NULL,
                surname VARCHAR(255) NOT NULL,
                email VARCHAR(255) UNIQUE NOT NULL CHECK (email ~ '^[A-Za-z0-9._%+-]+@[A-Za-z0-9.-]+\.[A-Za-z]{2,}$'),
                password VARCHAR(255) NOT NULL,
                group_id INTEGER NOT NULL REFERENCES groups(id) ON UPDATE CASCADE ON DELETE CASCADE,
                phone_number VARCHAR(16) NOT NULL CHECK (phone_number ~ '^\+[0-9]{9,15}$'),
                image VARCHAR(255),
                last_seen TIMESTAMP WITH TIME ZONE,
                role VARCHAR(20) NOT NULL
            );
            ]]>
        </sql>
    </changeSet>

    <changeSet id="create-subjects" author="Gleb Zapara">
        <sql dbms="postgresql" splitStatements="true" stripComments="true">
            <![CDATA[
            CREATE TABLE subjects(
                id INTEGER PRIMARY KEY GENERATED BY DEFAULT AS IDENTITY,
                name VARCHAR(255) NOT NULL,
                course SMALLINT NOT NULL CHECK (course >= 1 AND course <= 6),
                department_id INTEGER REFERENCES departments(id) NOT NULL,
                UNIQUE (name, course, department_id)
            );
            ]]>
        </sql>
    </changeSet>

    <changeSet id="create-lessons" author="Gleb Zapara">
        <sql dbms="postgresql" splitStatements="true" stripComments="true">
            <![CDATA[
            CREATE TABLE lessons(
                id INTEGER PRIMARY KEY GENERATED BY DEFAULT AS IDENTITY,
                subject_id INTEGER REFERENCES subjects(id) ON UPDATE CASCADE ON DELETE SET NULL,
                teacher_id INTEGER REFERENCES teachers(id) ON UPDATE CASCADE ON DELETE SET NULL,
                group_id INTEGER NOT NULL REFERENCES groups(id),
                start_time TIME NOT NULL,
                end_time TIME NOT NULL,
                day_of_week VARCHAR(20) NOT NULL
            );
            ]]>
        </sql>
    </changeSet>

    <changeSet id="create-lesson-groups" author="Gleb Zapara">
        <sql dbms="postgresql" splitStatements="true" stripComments="true">
            <![CDATA[
            CREATE TABLE lesson_groups(
                lesson_id INTEGER REFERENCES lessons(id) ON UPDATE CASCADE ON DELETE CASCADE,
                group_id INTEGER REFERENCES groups(id) ON UPDATE CASCADE ON DELETE CASCADE,
                PRIMARY KEY(lesson_id, group_id)
            );
            ]]>
        </sql>
    </changeSet>

    <changeSet id="create-grades" author="Gleb Zapara">
        <sql dbms="postgresql" splitStatements="true" stripComments="true">
            <![CDATA[
            CREATE TABLE grades(
                id INTEGER PRIMARY KEY GENERATED BY DEFAULT AS IDENTITY,
                student_id INTEGER NOT NULL REFERENCES students(id) ON DELETE CASCADE,
                subject_id INTEGER NOT NULL REFERENCES subjects(id) ON DELETE CASCADE,
                teacher_id INTEGER REFERENCES teachers(id) ON DELETE SET NULL,
                grade SMALLINT NOT NULL CHECK (grade >= 0 AND grade <= 100),
                created_at TIMESTAMP DEFAULT CURRENT_TIMESTAMP
            );
            ]]>
        </sql>
    </changeSet>

    <changeSet id="create-policies" author="Gleb Zapara">
        <sql dbms="postgresql" splitStatements="true" stripComments="true">
            <![CDATA[
            ALTER TABLE admins ENABLE ROW LEVEL SECURITY;
            ALTER TABLE departments ENABLE ROW LEVEL SECURITY;
            ALTER TABLE groups ENABLE ROW LEVEL SECURITY;
            ALTER TABLE students ENABLE ROW LEVEL SECURITY;
            ALTER TABLE subjects ENABLE ROW LEVEL SECURITY;
            ALTER TABLE teachers ENABLE ROW LEVEL SECURITY;
            ALTER TABLE lessons ENABLE ROW LEVEL SECURITY;
            ALTER TABLE lesson_groups ENABLE ROW LEVEL SECURITY;
            ALTER TABLE grades ENABLE ROW LEVEL SECURITY;
            ALTER TABLE databasechangelog ENABLE ROW LEVEL SECURITY;
            ALTER TABLE databasechangeloglock ENABLE ROW LEVEL SECURITY;

            CREATE POLICY backend_full_access_admins ON admins FOR ALL USING (true);
            CREATE POLICY backend_full_access_departments ON departments FOR ALL USING (true);
            CREATE POLICY backend_full_access_groups ON groups FOR ALL USING (true);
            CREATE POLICY backend_full_access_students ON students FOR ALL USING (true);
            CREATE POLICY backend_full_access_subjects ON subjects FOR ALL USING (true);
            CREATE POLICY backend_full_access_teachers ON teachers FOR ALL USING (true);
            CREATE POLICY backend_full_access_lessons ON lessons FOR ALL USING (true);
            CREATE POLICY backend_full_access_lesson_groups ON lesson_groups FOR ALL USING (true);
            CREATE POLICY backend_full_access_grades ON grades FOR ALL USING (true);
            CREATE POLICY backend_full_access_databasechangelog ON databasechangelog FOR ALL USING (true);
            CREATE POLICY backend_full_access_databasechangeloglock ON databasechangeloglock FOR ALL USING (true);
            ]]>
        </sql>
    </changeSet>

</databaseChangeLog>